basetrainer/__init__.py
basetrainer/callbacks/__init__.py
basetrainer/callbacks/accuracy_recorder.py
basetrainer/callbacks/callbacks.py
basetrainer/callbacks/log_history.py
basetrainer/callbacks/losses_recorder.py
basetrainer/callbacks/model_checkpoint.py
basetrainer/callbacks/multi_losses_recorder.py
basetrainer/criterion/__init__.py
basetrainer/criterion/criterion.py
basetrainer/dataloader/__init__.py
basetrainer/dataloader/data_resample.py
basetrainer/engine/__init__.py
basetrainer/engine/base.py
basetrainer/engine/comm.py
basetrainer/engine/engine.py
basetrainer/engine/launch.py
basetrainer/engine/ncnn_engine.py
basetrainer/engine/onnx_engine.py
basetrainer/engine/trainer.py
basetrainer/engine/trt_calibrator.py
basetrainer/engine/trt_engine.py
basetrainer/metric/__init__.py
basetrainer/metric/accuracy_recorder.py
basetrainer/metric/eval_tools/__init__.py
basetrainer/metric/eval_tools/acc.py
basetrainer/metric/eval_tools/classification_report.py
basetrainer/metric/eval_tools/eval_utils.py
basetrainer/metric/eval_tools/evaluate.py
basetrainer/metric/eval_tools/iou.py
basetrainer/metric/eval_tools/metrics.py
basetrainer/metric/eval_tools/pandas_tools.py
basetrainer/metric/eval_tools/pr.py
basetrainer/metric/eval_tools/roc.py
basetrainer/metric/eval_tools/verification.py
basetrainer/metric/map_tools/__init__.py
basetrainer/metric/map_tools/map_metric.py
basetrainer/metric/map_tools/evaluator/__init__.py
basetrainer/metric/map_tools/evaluator/bboxes_match.py
basetrainer/metric/map_tools/evaluator/iou.py
basetrainer/metric/map_tools/evaluator/map_eval.py
basetrainer/metric/map_tools/evaluator/map_eval_torch.py
basetrainer/models/__init__.py
basetrainer/models/build_models.py
basetrainer/optimizer/__init__.py
basetrainer/optimizer/build_optimizer.py
basetrainer/pruning/__init__.py
basetrainer/pruning/nni_pruning.py
basetrainer/pruning/slim_pruning.py
basetrainer/pruning/torch_pruning.py
basetrainer/scheduler/CosineAnnealingLR.py
basetrainer/scheduler/ExponentialLR.py
basetrainer-0.9.8.dist-info/LICENCE
basetrainer-0.9.8.dist-info/METADATA
basetrainer-0.9.8.dist-info/WHEEL
basetrainer-0.9.8.dist-info/top_level.txt
basetrainer-0.9.8.dist-info/RECORD
