Metadata-Version: 2.1
Name: basetrainer
Version: 0.9.8
Summary: basetrainer
Home-page: https://github.com/PanJinquan/Pytorch-Base-Trainer
Author: PanJinquan
Author-email: pan_jinquan@163.com
License: MIT
Platform: UNKNOWN
License-File: LICENCE
